CMakeLists.txt
LICENSE.md
MANIFEST.in
README.md
conanfile.py
pyproject.toml
setup.cfg
setup.py
docs/CMakeLists.txt
proposal.egg-info/PKG-INFO
proposal.egg-info/SOURCES.txt
proposal.egg-info/dependency_links.txt
proposal.egg-info/not-zip-safe
proposal.egg-info/top_level.txt
src/CMakeLists.txt
src/PROPOSAL/CMakeLists.txt
src/PROPOSAL/Config.cmake.in
src/PROPOSAL/PROPOSAL/CMakeLists.txt
src/PROPOSAL/PROPOSAL/Constants.h
src/PROPOSAL/PROPOSAL/DefaultFactory.h
src/PROPOSAL/PROPOSAL/EnergyCutSettings.h
src/PROPOSAL/PROPOSAL/Logging.h
src/PROPOSAL/PROPOSAL/PROPOSAL.h
src/PROPOSAL/PROPOSAL/Propagator.h
src/PROPOSAL/PROPOSAL/RegisteredInDefault.h
src/PROPOSAL/PROPOSAL/Secondaries.h
src/PROPOSAL/PROPOSAL/methods.h
src/PROPOSAL/PROPOSAL/version.h.in
src/PROPOSAL/PROPOSAL/crosssection/CrossSection.h
src/PROPOSAL/PROPOSAL/crosssection/CrossSectionBuilder.h
src/PROPOSAL/PROPOSAL/crosssection/CrossSectionDirect.h
src/PROPOSAL/PROPOSAL/crosssection/CrossSectionIntegral.h
src/PROPOSAL/PROPOSAL/crosssection/CrossSectionInterpolant.h
src/PROPOSAL/PROPOSAL/crosssection/CrossSectionMultiplier.h
src/PROPOSAL/PROPOSAL/crosssection/CrossSectionVector.h
src/PROPOSAL/PROPOSAL/crosssection/ParticleDefaultCrossSectionList.h
src/PROPOSAL/PROPOSAL/crosssection/CrossSectionDE2DX/AxisBuilderDE2DX.h
src/PROPOSAL/PROPOSAL/crosssection/CrossSectionDE2DX/CrossSectionDE2DX.h
src/PROPOSAL/PROPOSAL/crosssection/CrossSectionDE2DX/CrossSectionDE2DXBuilder.h
src/PROPOSAL/PROPOSAL/crosssection/CrossSectionDE2DX/CrossSectionDE2DXIntegral.h
src/PROPOSAL/PROPOSAL/crosssection/CrossSectionDE2DX/CrossSectionDE2DXInterpolant.h
src/PROPOSAL/PROPOSAL/crosssection/CrossSectionDEDX/AxisBuilderDEDX.h
src/PROPOSAL/PROPOSAL/crosssection/CrossSectionDEDX/CrossSectionDEDX.h
src/PROPOSAL/PROPOSAL/crosssection/CrossSectionDEDX/CrossSectionDEDXBuilder.h
src/PROPOSAL/PROPOSAL/crosssection/CrossSectionDEDX/CrossSectionDEDXIntegral.h
src/PROPOSAL/PROPOSAL/crosssection/CrossSectionDEDX/CrossSectionDEDXInterpolant.h
src/PROPOSAL/PROPOSAL/crosssection/CrossSectionDNDX/AxisBuilderDNDX.h
src/PROPOSAL/PROPOSAL/crosssection/CrossSectionDNDX/CrossSectionDNDX.h
