Metadata-Version: 2.1
Name: proposal
Version: 7.6.1
Summary: Monte Carlo simulation library to propagate leptons and gamma rays
Home-page: https://github.com/tudo-astroparticlephysics/PROPOSAL
Author: PROPOSAL Development Team
Author-email: jean-marco.alameddine@tu-dortmund.de
License: LGPLv3
Platform: unix
Classifier: Intended Audience :: Science/Research
Classifier: License :: OSI Approved :: GNU Lesser General Public License v3 (LGPLv3)
Classifier: Programming Language :: Python :: 3
Classifier: Programming Language :: Python :: 3.6
Classifier: Programming Language :: Python :: 3.7
Classifier: Programming Language :: Python :: 3.8
Classifier: Programming Language :: Python :: 3.9
Classifier: Programming Language :: Python :: 3.10
Classifier: Programming Language :: Python :: 3.11
Classifier: Programming Language :: Python :: Implementation :: CPython
Classifier: Topic :: Scientific/Engineering :: Physics
Classifier: Development Status :: 5 - Production/Stable
License-File: LICENSE.md
